tokentranslator/__init__.py
tokentranslator/demo_dialect.db
tokentranslator/configs/config_patterns_db.json
tokentranslator/configs/old.json
tokentranslator/db_models/__init__.py
tokentranslator/db_models/demo_dialect.db
tokentranslator/db_models/model_base.py
tokentranslator/db_models/model_examples.py
tokentranslator/db_models/model_main.py
tokentranslator/db_models/model_signatures.py
tokentranslator/db_models/model_stable.py
tokentranslator/db_models/model_tables.py
tokentranslator/db_models/data/__init__.py
tokentranslator/db_models/data/cs/__init__.py
tokentranslator/db_models/data/cs/demo_dialect.db
tokentranslator/db_models/data/cs/old_demo_dialect.db
tokentranslator/db_models/data/eqs/__init__.py
tokentranslator/db_models/data/eqs/demo_dialect.db
tokentranslator/db_models/data/eqs/old_demo_dialect.db
tokentranslator/db_models/data/eqs/old_tex_dialect.db
tokentranslator/db_models/data/eqs/tex_dialect.db
tokentranslator/db_models/data/examples/__init__.py
tokentranslator/db_models/data/examples/examples_parser_cs.db
tokentranslator/db_models/data/examples/examples_parser_eqs.db
tokentranslator/db_models/data/examples/examples_sampler.db
tokentranslator/db_models/data/sampling/__init__.py
tokentranslator/db_models/data/sampling/signatures.db
tokentranslator/env/__init__.py
tokentranslator/env/clause/__init__.py
tokentranslator/env/clause/clause_main.py
tokentranslator/env/clause/tests.py
tokentranslator/env/clause/parser/__init__.py
tokentranslator/env/clause/parser/parser_main.py
tokentranslator/env/equation/__init__.py
tokentranslator/env/equation/equation.py
tokentranslator/env/equation/tests.py
tokentranslator/env/equation/tests_lists.py
tokentranslator/env/equation/args/__init__.py
tokentranslator/env/equation/args/args_main.py
tokentranslator/env/equation/cas/__init__.py
tokentranslator/env/equation/cas/cas_main.py
tokentranslator/env/equation/data/__init__.py
tokentranslator/env/equation/data/grammars/__init__.py
tokentranslator-0.0.1.3.3.dist-info/LICENSE.md
tokentranslator-0.0.1.3.3.dist-info/METADATA
tokentranslator-0.0.1.3.3.dist-info/WHEEL
tokentranslator-0.0.1.3.3.dist-info/top_level.txt
tokentranslator-0.0.1.3.3.dist-info/RECORD
