Metadata-Version: 2.1
Name: tokentranslator
Version: 0.0.1.3.3
Summary: token translator framework
Home-page: https://github.com/tokentranslator-group/tokentranslator
Author: tokentranslator-group
Author-email: 
License: UNKNOWN
Platform: UNKNOWN
